LICENSE.txt
MANIFEST.in
README.rst
setup.cfg
setup.py
data/data_file
dl_package_test.egg-info/PKG-INFO
dl_package_test.egg-info/SOURCES.txt
dl_package_test.egg-info/dependency_links.txt
dl_package_test.egg-info/entry_points.txt
dl_package_test.egg-info/top_level.txt
sample/__init__.py
sample/hoge.py