Metadata-Version: 1.1
Name: dl-package-test
Version: 0.0.13
Summary: A test package for dl-environment
Home-page: UNKNOWN
Author: Hiroyasu OHYAMA
Author-email: user.localhost2000@gmail.com
License: MIT
Platform: UNKNOWN
Classifier: License :: OSI Approved :: MIT License
Classifier: Programming Language :: Python :: 3
Classifier: Programming Language :: Python :: 3.3
Classifier: Programming Language :: Python :: 3.4
Classifier: Programming Language :: Python :: 3.5
